hasbulla_boom/__init__.py
hasbulla_boom/database.py
hasbulla_boom/encryption.py
hasbulla_boom/server.py
hasbulla_boom/validators.py
hasbulla_boom-6.6.6.dist-info/WHEEL
hasbulla_boom-6.6.6.dist-info/METADATA
hasbulla_boom-6.6.6.dist-info/RECORD
